fifo/rtl/fifo.sv
module fifo #(
	parameter int WIDTH = 8,
	parameter int DEPTH = 16) (
	
	input logic clk,rst,
        input logic [WIDTH-1:0] din,
        input logic wr_en,rd_en,
        output logic full, empty,
        output logic [WIDTH-1:0] dout
        );

localparam int ADDR_WIDTH = $clog2(DEPTH);
localparam int COUNT_WIDTH = $clog2(DEPTH+1);

logic [WIDTH - 1:0] mem [0:DEPTH-1];

logic [ADDR_WIDTH-1:0] read_ptr, write_ptr;
logic [COUNT_WIDTH-1:0] count;

assign full = (count==DEPTH);
assign empty = (count==0);

always_ff @(posedge clk or posedge rst) begin
	if (rst) begin
		write_ptr <= '0;
	end
	else begin
		if (wr_en && !full) begin
			mem[write_ptr] <= din;
			write_ptr <= write_ptr + 1;
		end
	end

end

always_ff @(posedge clk or posedge rst) begin
        if (rst) begin
                read_ptr <= '0;
		dout <= '0;
        end
        else begin
                if (rd_en && !empty) begin
                        dout <= mem[read_ptr];
                        read_ptr <= read_ptr + 1;
                end
        end

end

always_ff @(posedge clk or posedge rst) begin
        if (rst) begin
                count <= '0;
        end
        else begin
                case({wr_en && !full, rd_en && !empty})
			2'b10: count <= count + 1;
			2'b01: count <= count - 1;
			default: count <= count;
		endcase
	end

end
endmodule

tb/tb_fifo_basic_1.sv
`timescale 1ns/1ps

module tb_fifo;
parameter int WIDTH = 8;
parameter int DEPTH = 16;

logic clk,rst,wr_en,rd_en;
logic [WIDTH-1:0] din,dout;
logic full,empty;

// =======================
// Functional Coverage Counters
// =======================

integer cov_write_only;
integer cov_read_only;
integer cov_simul_rw;
integer cov_empty_seen;
integer cov_full_seen;
integer cov_empty_to_nonempty;
integer cov_full_to_nonfull;

logic prev_empty;
logic prev_full;

initial begin
    cov_write_only        = 0;
    cov_read_only         = 0;
    cov_simul_rw           = 0;
    cov_empty_seen         = 0;
    cov_full_seen          = 0;
    cov_empty_to_nonempty  = 0;
    cov_full_to_nonfull    = 0;

    prev_empty = 1;
    prev_full  = 0;
end

fifo #(
	.WIDTH(WIDTH),
	.DEPTH(DEPTH))
	
	dut(.clk(clk),.rst(rst),.wr_en(wr_en),.rd_en(rd_en),
	.din(din),.dout(dout),.full(full),.empty(empty)
	);

initial clk=0;
always #10 clk = ~clk;

task reset_apply(); begin
		rst=1;
		wr_en = 0;
		rd_en = 0;
		din = '0;
		repeat(2)@ (posedge clk);
		rst = 0;	
	end
endtask

task write_fifo(input logic [WIDTH-1:0] data); begin
	@(posedge clk);
	if (!full) begin
		din = data;
		wr_en = 1;
		mem[write_idx] = data;
		write_idx++;
	end
	@(posedge clk);
		wr_en = 0;
	end
endtask

task read_fifo(); begin
	@(posedge clk);
	if(!empty)
		rd_en = 1;
	@(posedge clk);
	rd_en = 0;
end
endtask
	
int read_idx=0, write_idx=0;
logic [WIDTH-1:0] mem [0:DEPTH-1];

logic rd_en_d;
always_ff @(posedge clk) begin
    rd_en_d <= rd_en && !empty;
end

always @(posedge clk) begin
	if(!rst && rd_en_d && !empty) begin
		if(dout!=mem[read_idx]) begin
			$display("ERROR: Expected %d, Got %d at time %t", mem[read_idx],dout,$time());
			$stop;
		end
		read_idx++;
	end
end

always @(posedge clk) begin
    if (!rst) begin
        // Count overflow check
        if (dut.count > DEPTH) begin
            $error("ASSERTION FAILED: count overflow (count=%0d)", dut.count);
            $stop;
        end

        // Count underflow check
        if (dut.count < 0) begin
            $error("ASSERTION FAILED: count underflow (count=%0d)", dut.count);
            $stop;
        end
    end
end

always @(posedge clk) begin
    if (!rst) begin
        // No write when FIFO is full
        if (wr_en && full) begin
            $error("ASSERTION FAILED: Write when FIFO is full at time %0t", $time);
            $stop;
        end

        // No read when FIFO is empty
        if (rd_en && empty) begin
            $error("ASSERTION FAILED: Read when FIFO is empty at time %0t", $time);
            $stop;
        end
    end
end


initial begin
	$dumpfile("fifo.vcd");
	$dumpvars(0,tb_fifo);

	reset_apply();
	for (int i=0;i<5;i++) begin
		
		write_fifo(i + 8'd10);
	//	mem[write_idx] = i+ 8'd10;
	//        write_idx++;
	end

//	for (int j=0;j<5;j++) begin
//		read_fifo();
//	end
        report_coverage();
	#200;
	$display("All Tests Passed");
	$finish;
end

always @(posedge clk) begin
    if (!rst) begin
        // Write only
        if (wr_en && !rd_en &&!full)
            cov_write_only++;

        // Read only
        if (rd_en && !wr_en && !empty)
            cov_read_only++;

        // Simultaneous read & write
        if (wr_en && rd_en)
            cov_simul_rw++;

        // Empty / full observation
        if (empty)
            cov_empty_seen++;

        if (full)
            cov_full_seen++;

        // Transitions
        if (prev_empty && !empty)
            cov_empty_to_nonempty++;

        if (prev_full && !full)
            cov_full_to_nonfull++;

        prev_empty <= empty;
        prev_full  <= full;
    end
end

task report_coverage;
    begin
        $display("\n========== FIFO FUNCTIONAL COVERAGE ==========");
        $display("Write only operations      : %0d", cov_write_only);
        $display("Read only operations       : %0d", cov_read_only);
        $display("Simultaneous read/write    : %0d", cov_simul_rw);
        $display("Empty observed cycles      : %0d", cov_empty_seen);
        $display("Full observed cycles       : %0d", cov_full_seen);
        $display("Empty -> Non-empty         : %0d", cov_empty_to_nonempty);
        $display("Full -> Non-full           : %0d", cov_full_to_nonfull);
        $display("==============================================\n");
    end
endtask

endmodule

tb/fifo.vcd
$date
	Sat Dec 13 22:52:20 2025
$end
$version
	Icarus Verilog
$end
$timescale
	1ps
$end
$scope module tb_fifo $end
$var wire 1 ! full $end
$var wire 1 " empty $end
$var wire 8 # dout [7:0] $end
$var parameter 32 $ DEPTH $end
$var parameter 32 % WIDTH $end
$var reg 1 & clk $end
$var reg 8 ' din [7:0] $end
$var reg 1 ( prev_empty $end
$var reg 1 ) prev_full $end
$var reg 1 * rd_en $end
$var reg 1 + rd_en_d $end
$var reg 1 , rst $end
$var reg 1 - wr_en $end
$var integer 32 . cov_empty_seen [31:0] $end
$var integer 32 / cov_empty_to_nonempty [31:0] $end
$var integer 32 0 cov_full_seen [31:0] $end
$var integer 32 1 cov_full_to_nonfull [31:0] $end
$var integer 32 2 cov_read_only [31:0] $end
$var integer 32 3 cov_simul_rw [31:0] $end
$var integer 32 4 cov_write_only [31:0] $end
$var integer 32 5 read_idx [31:0] $end
$var integer 32 6 write_idx [31:0] $end
$scope module dut $end
$var wire 1 & clk $end
$var wire 8 7 din [7:0] $end
$var wire 1 * rd_en $end
$var wire 1 , rst $end
$var wire 1 - wr_en $end
$var wire 1 ! full $end
$var wire 1 " empty $end
$var parameter 32 8 ADDR_WIDTH $end
$var parameter 32 9 COUNT_WIDTH $end
$var parameter 32 : DEPTH $end
$var parameter 32 ; WIDTH $end
$var reg 5 < count [4:0] $end
$var reg 8 = dout [7:0] $end
$var reg 4 > read_ptr [3:0] $end
$var reg 4 ? write_ptr [3:0] $end
$upscope $end
$scope begin $ivl_for_loop0 $end
$var integer 32 @ i [31:0] $end
$upscope $end
$scope task read_fifo $end
$upscope $end
$scope task report_coverage $end
$upscope $end
$scope task reset_apply $end
$upscope $end
$scope task write_fifo $end
$var reg 8 A data [7:0] $end
$upscope $end
$upscope $end
$enddefinitions $end
$comment Show the parameter values. $end
$dumpall
b1000 ;
b10000 :
b101 9
b100 8
b1000 %
b10000 $
$end
#0
$dumpvars
bx A
b0 @
b0 ?
b0 >
b0 =
b0 <
b0 7
b0 6
b0 5
b0 4
b0 3
b0 2
b0 1
b0 0
b0 /
b0 .
0-
1,
x+
0*
0)
1(
b0 '
0&
b0 #
1"
0!
$end
#10000
0+
1&
#20000
0&
#30000
b1010 A
b1 .
0,
1&
#40000
0&
#50000
0"
b1 <
b1 ?
b10 .
b1 4
b1 6
1-
b1010 '
b1010 7
1&
#60000
0&
#70000
0(
b1011 A
b1 @
0-
b1 /
b10 4
1&
#80000
0&
#90000
b10 <
b10 ?
b11 4
b10 6
1-
b1011 '
b1011 7
1&
#100000
0&
#110000
b1100 A
b10 @
0-
b100 4
1&
#120000
0&
#130000
b11 <
b11 ?
b101 4
b11 6
1-
b1100 '
b1100 7
1&
#140000
0&
#150000
b1101 A
b11 @
0-
b110 4
1&
#160000
0&
#170000
b100 <
b100 ?
b111 4
b100 6
1-
b1101 '
b1101 7
1&
#180000
0&
#190000
b1110 A
b100 @
0-
b1000 4
1&
#200000
0&
#210000
b101 <
b101 ?
b1001 4
b101 6
1-
b1110 '
b1110 7
1&
#220000
0&
#230000
b101 @
0-
b1010 4
1&
#240000
0&
#250000
1&
#260000
0&
#270000
1&
#280000
0&
#290000
#250000
00
0&
